multiprocessing_utils/__init__.py
multiprocessing_utils/local.py
multiprocessing_utils/shared_lock.py
multiprocessing_utils/tests/__init__.py
multiprocessing_utils/tests/helpers.py
multiprocessing_utils/tests/test_local.py
multiprocessing_utils/tests/test_shared_lock.py
multiprocessing_utils/tests/test_shared_rlock.py
multiprocessing_utils-0.4.dist-info/DESCRIPTION.rst
multiprocessing_utils-0.4.dist-info/METADATA
multiprocessing_utils-0.4.dist-info/RECORD
multiprocessing_utils-0.4.dist-info/WHEEL
multiprocessing_utils-0.4.dist-info/metadata.json
multiprocessing_utils-0.4.dist-info/top_level.txt
