Metadata-Version: 1.1
Name: multiprocessing-utils
Version: 0.4
Summary: Multiprocessing utils (shared locks and thread locals)
Home-page: https://github.com/daggaz/python-multiprocessing-utils
Author: Jamie Cockburn and Andrew Binnie
Author-email: jamie_cockburn@hotmail.co.uk
License: MIT
Platform: UNKNOWN
Classifier: Development Status :: 4 - Beta
Classifier: Intended Audience :: Developers
Classifier: Topic :: Software Development :: Libraries :: Python Modules
Classifier: License :: OSI Approved :: MIT License
Classifier: Programming Language :: Python :: 2
Classifier: Programming Language :: Python :: 2.7
Classifier: Programming Language :: Python :: 3
Classifier: Programming Language :: Python :: 3.3
Classifier: Programming Language :: Python :: 3.4
Classifier: Programming Language :: Python :: 3.5
Classifier: Programming Language :: Python :: 3.6
